geodex/__init__.py
geodex/main.py
geodex/search.py
geodex/utils.py
geodex/version.py
geodex-0.1.2.dist-info/DESCRIPTION.rst
geodex-0.1.2.dist-info/METADATA
geodex-0.1.2.dist-info/RECORD
geodex-0.1.2.dist-info/WHEEL
geodex-0.1.2.dist-info/dependency_links.txt
geodex-0.1.2.dist-info/entry_points.txt
geodex-0.1.2.dist-info/metadata.json
geodex-0.1.2.dist-info/top_level.txt
