Metadata-Version: 2.0
Name: geodex
Version: 0.1.2
Summary: A tool to find all geospatial tile indices overlapping an arbitrary boundary at an arbitrary zoom.
Home-page: https://github.com/developmentseed/geodex
Author: Development Seed
Author-email: UNKNOWN
License: MIT
Platform: UNKNOWN
Classifier: Intended Audience :: Developers
Classifier: License :: Freeware
Classifier: Programming Language :: Python :: 3.5
Classifier: Programming Language :: Python :: 3.6
Requires-Dist: pygeotile (>=1.0.5)
Requires-Dist: shapely (>=1.6.4)
